MANIFEST.in
README.rst
setup.cfg
setup.py
sphinx_rfc2119.py
_static/css/rfc2119.css
sphinx_rfc2119.egg-info/PKG-INFO
sphinx_rfc2119.egg-info/SOURCES.txt
sphinx_rfc2119.egg-info/dependency_links.txt
sphinx_rfc2119.egg-info/requires.txt
sphinx_rfc2119.egg-info/top_level.txt