Metadata-Version: 1.1
Name: sphinx-rfc2119
Version: 0.0.9
Summary: RFC2119 directives for Sphinx documentation
Home-page: https://github.com/monkeypants/sphinx.rfc2119
Author: Chris Gough
Author-email: christopher.d.gough-pypi@gmail.com
License: GPLv3
Keywords: RFC2119 directives Sphinx docutils
Platform: UNKNOWN
Classifier: Development Status :: 3 - Alpha
Classifier: Intended Audience :: Developers
Classifier: License :: OSI Approved :: GNU General Public License v3 or later (GPLv3+)
Classifier: Programming Language :: Python :: 2.7
